Workbook
Name Priority: #REF!
Name Status: 'listas desplegables'!$D$5:$D$7
Name Type: '[1]Risk Assessment & Control'!#REF!
Name Type: '[2]Maintenance Work Order'!#REF!
Name YesNo: 'listas desplegables'!$B$5:$B$6

Sheet Presupuesto del proyecto
B1: Presupuesto de proyecto
B2: FARMAPS | H2: Mano de Obra | K2: Materiales | N2: Costos Fijos | Q2: Balance
B3: TAREA | C3: DESCRIPCION | D3: ESTADO | E3: FECHA INICIO PLANIFICADA | F3: FECHA INICIO REAL | G3: FECHA FIN | H3: HORAS | I3: VALOR HORA | J3: TOTAL MANO DE OBRA | K3: UNIDADES | L3: VALOR UNIDAD | M3: TOTAL MATERIALES | N3: VIAJES | O3: EQUIPOS | P3: MISCELANEOS | Q3: PRESUPUESTO | R3: REAL | S3: Diferencia (Menos / Más del Presupuesto)
B4: FARMAPS | C4: Desarrollo técnico
B5: D01 | C5: Entorno y datos | D5: Completo | E5: 46300 | F5: =IF(ISNUMBER('Registro real'!C2),'Registro real'!C2,"") | G5: 46310 | H5: =SUM('Detalle de esfuerzo'!C2,'Detalle de esfuerzo'!C3,'Detalle de esfuerzo'!C4) -> 9 | I5: 15000 | J5: =H5*I5 -> 135000 | K5: 0 | L5: 0 | M5: =K5*L5 -> 0 | N5: 0 | O5: 0 | P5: 0 | Q5: =SUM(J5,M5:P5) -> 135000 | R5: =IF(ISNUMBER('Registro real'!D2),'Registro real'!D2,"") | S5: =IF(ISNUMBER(R5),R5-Q5,"")
B6: D02 | C6: Servicio de búsqueda | D6: Completo | E6: 46310 | F6: =IF(ISNUMBER('Registro real'!C3),'Registro real'!C3,"") | G6: 46313 | H6: =SUM('Detalle de esfuerzo'!C5) -> 6 | I6: 15000 | J6: =H6*I6 -> 90000 | K6: 0 | L6: 0 | M6: =K6*L6 -> 0 | N6: 0 | O6: 0 | P6: 0 | Q6: =SUM(J6,M6:P6) -> 90000 | R6: =IF(ISNUMBER('Registro real'!D3),'Registro real'!D3,"") | S6: =IF(ISNUMBER(R6),R6-Q6,"")
B7: D03 | C7: Administración | D7: Completo | E7: 46314 | F7: =IF(ISNUMBER('Registro real'!C4),'Registro real'!C4,"") | G7: 46318 | H7: =SUM('Detalle de esfuerzo'!C6,'Detalle de esfuerzo'!C7) -> 7 | I7: 15000 | J7: =H7*I7 -> 105000 | K7: 0 | L7: 0 | M7: =K7*L7 -> 0 | N7: 0 | O7: 0 | P7: 0 | Q7: =SUM(J7,M7:P7) -> 105000 | R7: =IF(ISNUMBER('Registro real'!D4),'Registro real'!D4,"") | S7: =IF(ISNUMBER(R7),R7-Q7,"")
B8: D04 | C8: Interfaz web | D8: Completo | E8: 46319 | F8: =IF(ISNUMBER('Registro real'!C5),'Registro real'!C5,"") | G8: 46332 | H8: =SUM('Detalle de esfuerzo'!C8,'Detalle de esfuerzo'!C12) -> 9 | I8: 15000 | J8: =H8*I8 -> 135000 | K8: 0 | L8: 0 | M8: =K8*L8 -> 0 | N8: 0 | O8: 0 | P8: 0 | Q8: =SUM(J8,M8:P8) -> 135000 | R8: =IF(ISNUMBER('Registro real'!D5),'Registro real'!D5,"") | S8: =IF(ISNUMBER(R8),R8-Q8,"")
B9: D05 | C9: Mapa y ubicación | D9: Completo | E9: 46322 | F9: =IF(ISNUMBER('Registro real'!C6),'Registro real'!C6,"") | G9: 46327 | H9: =SUM('Detalle de esfuerzo'!C9,'Detalle de esfuerzo'!C10) -> 9 | I9: 15000 | J9: =H9*I9 -> 135000 | K9: 0 | L9: 0 | M9: =K9*L9 -> 0 | N9: 0 | O9: 0 | P9: 0 | Q9: =SUM(J9,M9:P9) -> 135000 | R9: =IF(ISNUMBER('Registro real'!D6),'Registro real'!D6,"") | S9: =IF(ISNUMBER(R9),R9-Q9,"")
B10: D06 | C10: Comparación | D10: Completo | E10: 46328 | F10: =IF(ISNUMBER('Registro real'!C7),'Registro real'!C7,"") | G10: 46329 | H10: =SUM('Detalle de esfuerzo'!C11) -> 4 | I10: 15000 | J10: =H10*I10 -> 60000 | K10: 0 | L10: 0 | M10: =K10*L10 -> 0 | N10: 0 | O10: 0 | P10: 0 | Q10: =SUM(J10,M10:P10) -> 60000 | R10: =IF(ISNUMBER('Registro real'!D7),'Registro real'!D7,"") | S10: =IF(ISNUMBER(R10),R10-Q10,"")
B11: D07 | C11: Integración | D11: Completo | E11: 46335 | F11: =IF(ISNUMBER('Registro real'!C8),'Registro real'!C8,"") | G11: 46337 | H11: =SUM('Detalle de esfuerzo'!C14,'Detalle de esfuerzo'!C15) -> 5 | I11: 15000 | J11: =H11*I11 -> 75000 | K11: 0 | L11: 0 | M11: =K11*L11 -> 0 | N11: 0 | O11: 0 | P11: 0 | Q11: =SUM(J11,M11:P11) -> 75000 | R11: =IF(ISNUMBER('Registro real'!D8),'Registro real'!D8,"") | S11: =IF(ISNUMBER(R11),R11-Q11,"")
B12: D08 | C12: Pruebas y correcciones | D12: Completo | E12: 46338 | F12: =IF(ISNUMBER('Registro real'!C9),'Registro real'!C9,"") | G12: 46346 | H12: =SUM('Detalle de esfuerzo'!C16,'Detalle de esfuerzo'!C17,'Detalle de esfuerzo'!C18,'Detalle de esfuerzo'!C19,'Detalle de esfuerzo'!C20) -> 16 | I12: 15000 | J12: =H12*I12 -> 240000 | K12: 0 | L12: 0 | M12: =K12*L12 -> 0 | N12: 0 | O12: 0 | P12: 0 | Q12: =SUM(J12,M12:P12) -> 240000 | R12: =IF(ISNUMBER('Registro real'!D9),'Registro real'!D9,"") | S12: =IF(ISNUMBER(R12),R12-Q12,"")
B13: D09 | C13: Despliegue y versión final | D13: En Progreso | E13: 46333 | F13: =IF(ISNUMBER('Registro real'!C10),'Registro real'!C10,"") | G13: 46348 | H13: =SUM('Detalle de esfuerzo'!C13,'Detalle de esfuerzo'!C21,'Detalle de esfuerzo'!C22) -> 8 | I13: 15000 | J13: =H13*I13 -> 120000 | K13: 0 | L13: 0 | M13: =K13*L13 -> 0 | N13: 0 | O13: 0 | P13: 0 | Q13: =SUM(J13,M13:P13) -> 120000 | R13: =IF(ISNUMBER('Registro real'!D10),'Registro real'!D10,"") | S13: =IF(ISNUMBER(R13),R13-Q13,"")
B14: SUBTOTAL | H14: =SUM(H5:H13) -> 73 | J14: =SUM(J5:J13) -> 1095000 | M14: =SUM(M5:M13) -> 0 | N14: =SUM(N5:N13) -> 0 | O14: =SUM(O5:O13) -> 0 | P14: =SUM(P5:P13) -> 0 | Q14: =SUM(Q5:Q13) -> 1095000 | R14: =IF(COUNT(R5:R13)=ROWS(R5:R13),SUM(R5:R13),"") | S14: =IF(ISNUMBER(R14),R14-Q14,"")
B16: El usuario debe completar solo las celdas no sombreadas. | H16: Mano de Obra | K16: Materiales | N16: Costos Fijos | Q16: Balance
B17: TAREA | C17: DESCRIPCION | D17: ESTADO | E17: FECHA INICIO PLANIFICADA | F17: FECHA INICIO REAL | G17: FECHA FIN | H17: HORAS | I17: VALOR HORA | J17: TOTAL MANO DE OBRA | K17: UNIDADES | L17: VALOR UNIDAD | M17: TOTAL MATERIALES | N17: VIAJES | O17: EQUIPOS | P17: MISCELANEOS | Q17: PRESUPUESTO | R17: REAL | S17: Diferencia (Menos / Más del Presupuesto)
B18: FARMAPS | C18: Trabajo académico y recursos
B19: G01 | C19: Gestión y requisitos | D19: Completo | E19: 46237 | F19: =IF(ISNUMBER('Registro real'!C11),'Registro real'!C11,"") | G19: 46348 | H19: =SUM('Detalle de esfuerzo'!C23) -> 20 | I19: 15000 | J19: =H19*I19 -> 300000 | K19: 0 | L19: 0 | M19: =K19*L19 -> 0 | N19: 0 | O19: 0 | P19: 0 | Q19: =SUM(J19,M19:P19) -> 300000 | R19: =IF(ISNUMBER('Registro real'!D11),'Registro real'!D11,"") | S19: =IF(ISNUMBER(R19),R19-Q19,"")
B20: G02 | C20: Diseño previo | D20: Completo | E20: 46279 | F20: =IF(ISNUMBER('Registro real'!C12),'Registro real'!C12,"") | G20: 46337 | H20: =SUM('Detalle de esfuerzo'!C24) -> 16 | I20: 15000 | J20: =H20*I20 -> 240000 | K20: 0 | L20: 0 | M20: =K20*L20 -> 0 | N20: 0 | O20: 0 | P20: 0 | Q20: =SUM(J20,M20:P20) -> 240000 | R20: =IF(ISNUMBER('Registro real'!D12),'Registro real'!D12,"") | S20: =IF(ISNUMBER(R20),R20-Q20,"")
B21: G03 | C21: Documentación y cierre | D21: En Progreso | E21: 46342 | F21: =IF(ISNUMBER('Registro real'!C13),'Registro real'!C13,"") | G21: 46348 | H21: =SUM('Detalle de esfuerzo'!C25) -> 11 | I21: 15000 | J21: =H21*I21 -> 165000 | K21: 0 | L21: 0 | M21: =K21*L21 -> 0 | N21: 0 | O21: 0 | P21: 0 | Q21: =SUM(J21,M21:P21) -> 165000 | R21: =IF(ISNUMBER('Registro real'!D13),'Registro real'!D13,"") | S21: =IF(ISNUMBER(R21),R21-Q21,"")
B22: R01 | C22: Conectividad y energía | D22: En Progreso | E22: 46237 | F22: =IF(ISNUMBER('Registro real'!C14),'Registro real'!C14,"") | G22: 46348 | H22: 0 | I22: 0 | J22: =H22*I22 -> 0 | K22: 0 | L22: 0 | M22: =K22*L22 -> 0 | N22: 0 | O22: 0 | P22: 100000 | Q22: =SUM(J22,M22:P22) -> 100000 | R22: =IF(ISNUMBER('Registro real'!D14),'Registro real'!D14,"") | S22: =IF(ISNUMBER(R22),R22-Q22,"")
B23: R02 | C23: Reserva de contingencia | D23: En Espera | E23: 46237 | F23: =IF(ISNUMBER('Registro real'!C15),'Registro real'!C15,"") | G23: 46348 | H23: 0 | I23: 0 | J23: =H23*I23 -> 0 | K23: 0 | L23: 0 | M23: =K23*L23 -> 0 | N23: 0 | O23: 0 | P23: 50000 | Q23: =SUM(J23,M23:P23) -> 50000 | R23: =IF(ISNUMBER('Registro real'!D15),'Registro real'!D15,"") | S23: =IF(ISNUMBER(R23),R23-Q23,"")
B24: R03 | C24: Equipo existente | D24: En Progreso | E24: 46237 | F24: =IF(ISNUMBER('Registro real'!C16),'Registro real'!C16,"") | G24: 46348 | H24: 0 | I24: 0 | J24: =H24*I24 -> 0 | K24: 0 | L24: 0 | M24: =K24*L24 -> 0 | N24: 0 | O24: 0 | P24: 0 | Q24: =SUM(J24,M24:P24) -> 0 | R24: =IF(ISNUMBER('Registro real'!D16),'Registro real'!D16,"") | S24: =IF(ISNUMBER(R24),R24-Q24,"")
B25: R04 | C25: Software y base de datos | D25: En Progreso | E25: 46300 | F25: =IF(ISNUMBER('Registro real'!C17),'Registro real'!C17,"") | G25: 46348 | H25: 0 | I25: 0 | J25: =H25*I25 -> 0 | K25: 0 | L25: 0 | M25: =K25*L25 -> 0 | N25: 0 | O25: 0 | P25: 0 | Q25: =SUM(J25,M25:P25) -> 0 | R25: =IF(ISNUMBER('Registro real'!D17),'Registro real'!D17,"") | S25: =IF(ISNUMBER(R25),R25-Q25,"")
B26: R05 | C26: Mapa y alojamiento | D26: En Progreso | E26: 46300 | F26: =IF(ISNUMBER('Registro real'!C18),'Registro real'!C18,"") | G26: 46348 | H26: 0 | I26: 0 | J26: =H26*I26 -> 0 | K26: 0 | L26: 0 | M26: =K26*L26 -> 0 | N26: 0 | O26: 0 | P26: 0 | Q26: =SUM(J26,M26:P26) -> 0 | R26: =IF(ISNUMBER('Registro real'!D18),'Registro real'!D18,"") | S26: =IF(ISNUMBER(R26),R26-Q26,"")
B27: R06 | C27: Materiales y viajes | D27: En Espera | E27: 46237 | F27: =IF(ISNUMBER('Registro real'!C19),'Registro real'!C19,"") | G27: 46348 | H27: 0 | I27: 0 | J27: =H27*I27 -> 0 | K27: 0 | L27: 0 | M27: =K27*L27 -> 0 | N27: 0 | O27: 0 | P27: 0 | Q27: =SUM(J27,M27:P27) -> 0 | R27: =IF(ISNUMBER('Registro real'!D19),'Registro real'!D19,"") | S27: =IF(ISNUMBER(R27),R27-Q27,"")
B28: SUBTOTAL | H28: =SUM(H19:H27) -> 47 | J28: =SUM(J19:J27) -> 705000 | M28: =SUM(M19:M27) -> 0 | N28: =SUM(N19:N27) -> 0 | O28: =SUM(O19:O27) -> 0 | P28: =SUM(P19:P27) -> 150000 | Q28: =SUM(Q19:Q27) -> 855000 | R28: =IF(COUNT(R19:R27)=ROWS(R19:R27),SUM(R19:R27),"") | S28: =IF(ISNUMBER(R28),R28-Q28,"")
B30: TOTAL | C30: FARMAPS (COP) | H30: =SUM(H14,H28) -> 120 | J30: =SUM(J14,J28) -> 1800000 | M30: =SUM(M14,M28) -> 0 | N30: =SUM(N14,N28) -> 0 | O30: =SUM(O14,O28) -> 0 | P30: =SUM(P14,P28) -> 150000 | Q30: =SUM(Q14,Q28) -> 1950000 | R30: =IF(COUNT(R14,R28)=2,SUM(R14,R28),"") | S30: =IF(ISNUMBER(R30),R30-Q30,"")

Sheet listas desplegables
B1: listas desplegables
B2: SI / NO | D2: PRIORIDAD | F2: ESTADO
B3: Si | D3: Baja | F3: No Iniciado
B4: No | D4: Media | F4: En Progreso
D5: Alta | F5: Completo
F6: Requiere Revisión
F7: Aprobado
F8: Atrasado
F9: En Espera

Sheet Detalle de esfuerzo
A1: ID | B1: Actividad / rubro | C1: Horas estimadas | D1: Valor hora (COP) | E1: Costo estimado (COP) | F1: Alcance | G1: Responsable
A2: A01 | B2: Configurar el entorno y el repositorio | C2: 2 | D2: 15000 | E2: =C2*D2 -> 30000 | F2: Desarrollo técnico | G2: Juan David Cardozo Prada
A3: A02 | B3: Implementar la base de datos y sus validaciones | C3: 4 | D3: 15000 | E3: =C3*D3 -> 60000 | F3: Desarrollo técnico | G3: Juan David Cardozo Prada
A4: A03 | B4: Preparar el catálogo de demostración | C4: 3 | D4: 15000 | E4: =C4*D4 -> 45000 | F4: Desarrollo técnico | G4: Juan David Cardozo Prada
A5: A04 | B5: Desarrollar consultas y búsqueda de medicamentos | C5: 6 | D5: 15000 | E5: =C5*D5 -> 90000 | F5: Desarrollo técnico | G5: Juan David Cardozo Prada
A6: A05 | B6: Implementar el acceso administrativo | C6: 3 | D6: 15000 | E6: =C6*D6 -> 45000 | F6: Desarrollo técnico | G6: Juan David Cardozo Prada
A7: A06 | B7: Implementar la gestión del catálogo | C7: 4 | D7: 15000 | E7: =C7*D7 -> 60000 | F7: Desarrollo técnico | G7: Juan David Cardozo Prada
A8: A07 | B8: Desarrollar la búsqueda y lista de resultados | C8: 4 | D8: 15000 | E8: =C8*D8 -> 60000 | F8: Desarrollo técnico | G8: Juan David Cardozo Prada
A9: A08 | B9: Integrar el mapa y las fichas de farmacias | C9: 4 | D9: 15000 | E9: =C9*D9 -> 60000 | F9: Desarrollo técnico | G9: Juan David Cardozo Prada
A10: A09 | B10: Implementar ubicación y distancia aproximada | C10: 5 | D10: 15000 | E10: =C10*D10 -> 75000 | F10: Desarrollo técnico | G10: Juan David Cardozo Prada
A11: A10 | B11: Implementar comparación y ordenamiento | C11: 4 | D11: 15000 | E11: =C11*D11 -> 60000 | F11: Desarrollo técnico | G11: Juan David Cardozo Prada
A12: A11 | B12: Integrar interfaz adaptable y manejo de errores | C12: 5 | D12: 15000 | E12: =C12*D12 -> 75000 | F12: Desarrollo técnico | G12: Juan David Cardozo Prada
A13: A12 | B13: Preparar despliegue demostrativo y respaldos | C13: 3 | D13: 15000 | E13: =C13*D13 -> 45000 | F13: Desarrollo técnico | G13: Juan David Cardozo Prada
... A25: G03 | B25: Manuales, informe, sustentación y entrega académica | C25: 11 | D25: 15000 | E25: =C25*D25 -> 165000 | F25: Trabajo académico no técnico | G25: Juan David Cardozo Prada
A26: TOTAL | B26: Proyecto completo | C26: =SUM(C2:C25) -> 120 | E26: =SUM(E2:E25) -> 1800000

Sheet Registro real
A1: Rubro | B1: Descripción | C1: Inicio real | D1: Costo real valorado (COP) | E1: Soporte / observación
A2: D01 | B2: Entorno y datos | E2: Completado según el cronograma del 25/09/2026 (ejecutado antes de su ventana). No hay registro de horas reales; costo real sin reportar.
A3: D02 | B3: Servicio de búsqueda | E3: Completado según el cronograma del 25/09/2026 (ejecutado antes de su ventana). No hay registro de horas reales; costo real sin reportar.
A4: D03 | B4: Administración | E4: Completado según el cronograma del 25/09/2026 (ejecutado antes de su ventana). No hay registro de horas reales; costo real sin reportar.
A5: D04 | B5: Interfaz web | E5: Completado según el cronograma del 25/09/2026 (ejecutado antes de su ventana). No hay registro de horas reales; costo real sin reportar.
A6: D05 | B6: Mapa y ubicación | E6: Completado según el cronograma del 25/09/2026 (ejecutado antes de su ventana). No hay registro de horas reales; costo real sin reportar.
A7: D06 | B7: Comparación | E7: Completado según el cronograma del 25/09/2026 (ejecutado antes de su ventana). No hay registro de horas reales; costo real sin reportar.
A8: D07 | B8: Integración | E8: Completado según el cronograma del 25/09/2026 (ejecutado antes de su ventana). No hay registro de horas reales; costo real sin reportar.
A9: D08 | B9: Pruebas y correcciones | E9: Completado según el cronograma del 25/09/2026 (ejecutado antes de su ventana). No hay registro de horas reales; costo real sin reportar.
A10: D09 | B10: Despliegue y versión final | E10: A12 completada; A20 y A21 programadas para el 21 y el 22/11/2026. Costo real sin reportar.
A11: G01 | B11: Gestión y requisitos | E11: Completado según el cronograma del 25/09/2026. No hay registro de horas reales; costo real sin reportar.
A12: G02 | B12: Diseño previo | E12: Completado según el cronograma del 25/09/2026. No hay registro de horas reales; costo real sin reportar.
A13: G03 | B13: Documentación y cierre | E13: Programado del 16/11 al 22/11/2026.
... A19: R06 | B19: Materiales y viajes | E19: Sin compras de materiales ni desplazamientos a la fecha.

Sheet Criterios del presupuesto
A1: Concepto | B1: Criterio
A2: Referencia | B2: Acta_de_Constitucion.docx actualizada por el estudiante, lista de actividades técnicas vigente y cronograma del proyecto (Cronograma.xlsx). Elaboración: 17/09/2026; actualización de fechas y estados: 25/09/2026. Se conserva el total de COP 1.950.000 del acta.
A3: Alcance del presupuesto | B3: Presupuesto del proyecto completo, a diferencia de la lista y EDT que cubren únicamente el desarrollo. Los dos bloques de la primera hoja corresponden al mismo Farmaps, no a dos proyectos.
A4: Trabajo individual | B4: Juan David Cardozo Prada ejecuta todo el trabajo. Las 120 horas a COP 15.000/h representan COP 1.800.000 de valoración académica del esfuerzo; no son contratación ni pago obligatorio al estudiante.
A5: Desarrollo técnico | B5: 73 horas = COP 1.095.000. Las 21 actividades A01–A21 se agrupan en nueve rubros sin omisiones ni duplicaciones; el detalle por actividad se conserva en Detalle de esfuerzo.
A6: Trabajo académico complementario | B6: 47 horas = COP 705.000: gestión y requisitos 20 h, diseño y preparación 16 h, manuales/informe/sustentación/entrega 11 h. Son las actividades excluidas de la lista técnica, no nuevas horas añadidas al total.
A7: Recursos y contingencia | B7: COP 100.000 de conectividad y energía, más COP 50.000 de reserva. Se registran una sola vez como misceláneos de la plantilla. Total de gastos/reserva estimado: COP 150.000; no representa gasto ya ejecutado.
A8: Sin costo adicional | B8: Equipo existente, software, base de datos, mapa y alojamiento gratuito: COP 0 adicional previsto. Sin compra de dominio, materiales ni viajes. Los ceros son supuestos presupuestarios, no cotizaciones ni confirmación de gratuidad ilimitada.
A9: Fechas y disponibilidad | B9: Según el cronograma, el proyecto va del 03/08/2026 al 22/11/2026 (112 días), antes de la última semana de noviembre. Desarrollo técnico del 05/10 al 22/11/2026; publicación final y entrega académica el 22/11/2026. Las fechas de los rubros son las ventanas de sus actividades, no dedicación continua o simultánea.
A10: Fecha y costo real | B10: No se registraron fechas efectivas por rubro ni horas reales, por eso el costo real sigue vacío. En Registro real solo se anota el soporte u observación de cada rubro. No se copian las estimaciones como si fueran ejecución real.
A11: Interpretación del real | B11: Para mano de obra propia, registrar la valoración del esfuerzo efectivamente realizado con respaldo de horas; para recursos, el gasto comprobado. El total combina valoración y gastos, por lo que no equivale al dinero desembolsado.
A12: Estado inicial | B12: Estado al 25/09/2026 según el cronograma: D01-D08, G01 y G02 Completo; D09 En Progreso (A12 completa, A20 y A21 pendientes); G03 No Iniciado. Recursos: R01, R03, R04 y R05 En Progreso porque están en uso; R02 y R06 En Espera. No se presume que existan aprobación, desembolsos o financiación.
... A16: Formato | B16: Primera hoja con distribución, encabezados, tipografía, colores, anchos y combinaciones de celdas de la plantilla original. Las actividades usan nombres compactos y comentarios para mostrar el detalle sin ensanchar columnas. Solo se amplían las filas de datos para legibilidad y se añade un total general con el estilo de subtotal original. Las hojas de apoyo conservan el desglose y el registro real.
